azure/mgmt/mobilenetwork/__init__.py
azure/mgmt/mobilenetwork/_configuration.py
azure/mgmt/mobilenetwork/_mobile_network_management_client.py
azure/mgmt/mobilenetwork/_patch.py
azure/mgmt/mobilenetwork/_serialization.py
azure/mgmt/mobilenetwork/_vendor.py
azure/mgmt/mobilenetwork/_version.py
azure/mgmt/mobilenetwork/py.typed
azure/mgmt/mobilenetwork/aio/__init__.py
azure/mgmt/mobilenetwork/aio/_configuration.py
azure/mgmt/mobilenetwork/aio/_mobile_network_management_client.py
azure/mgmt/mobilenetwork/aio/_patch.py
azure/mgmt/mobilenetwork/aio/operations/__init__.py
azure/mgmt/mobilenetwork/aio/operations/_attached_data_networks_operations.py
azure/mgmt/mobilenetwork/aio/operations/_data_networks_operations.py
azure/mgmt/mobilenetwork/aio/operations/_diagnostics_packages_operations.py
azure/mgmt/mobilenetwork/aio/operations/_extended_ue_information_operations.py
azure/mgmt/mobilenetwork/aio/operations/_mobile_networks_operations.py
azure/mgmt/mobilenetwork/aio/operations/_operations.py
azure/mgmt/mobilenetwork/aio/operations/_packet_captures_operations.py
azure/mgmt/mobilenetwork/aio/operations/_packet_core_control_plane_versions_operations.py
azure/mgmt/mobilenetwork/aio/operations/_packet_core_control_planes_operations.py
azure/mgmt/mobilenetwork/aio/operations/_packet_core_data_planes_operations.py
azure/mgmt/mobilenetwork/aio/operations/_patch.py
azure/mgmt/mobilenetwork/aio/operations/_routing_info_operations.py
azure/mgmt/mobilenetwork/aio/operations/_services_operations.py
azure/mgmt/mobilenetwork/aio/operations/_sim_groups_operations.py
azure/mgmt/mobilenetwork/aio/operations/_sim_policies_operations.py
azure/mgmt/mobilenetwork/aio/operations/_sims_operations.py
azure/mgmt/mobilenetwork/aio/operations/_sites_operations.py
azure/mgmt/mobilenetwork/aio/operations/_slices_operations.py
azure/mgmt/mobilenetwork/aio/operations/_ue_information_operations.py
azure/mgmt/mobilenetwork/models/__init__.py
azure_mgmt_mobilenetwork-3.3.1.dist-info/licenses/LICENSE
azure_mgmt_mobilenetwork-3.3.1.dist-info/METADATA
azure_mgmt_mobilenetwork-3.3.1.dist-info/WHEEL
azure_mgmt_mobilenetwork-3.3.1.dist-info/top_level.txt
azure_mgmt_mobilenetwork-3.3.1.dist-info/RECORD
